{
  "Prompt_1": {
    "error": "Failed to process Prompt_1: Unknown prompt format"
  },
  "Prompt_2": {
    "error": "Failed to process Prompt_2: Unknown prompt format"
  },
  "Prompt_3": {
    "error": "Failed to process Prompt_3: Unknown prompt format"
  },
  "Prompt_4": {
    "error": "Failed to process Prompt_4: Unknown prompt format"
  },
  "Prompt_5": {
    "error": "Failed to process Prompt_5: Unknown prompt format"
  },
  "Prompt_6": {
    "error": "Failed to process Prompt_6: Unknown prompt format"
  },
  "Prompt_7": {
    "error": "Failed to process Prompt_7: Unknown prompt format"
  },
  "Prompt_8": {
    "error": "Failed to process Prompt_8: Unknown prompt format"
  },
  "Prompt_9": {
    "error": "Failed to process Prompt_9: Unknown prompt format"
  },
  "Prompt_10": {
    "error": "Failed to process Prompt_10: Unknown prompt format"
  },
  "Prompt_11": {
    "error": "Failed to process Prompt_11: Unknown prompt format"
  },
  "Prompt_12": {
    "error": "Failed to process Prompt_12: Unknown prompt format"
  },
  "Prompt_13": {
    "error": "Failed to process Prompt_13: Unknown prompt format"
  },
  "Prompt_14": {
    "error": "Failed to process Prompt_14: Unknown prompt format"
  },
  "Prompt_15": {
    "error": "Failed to process Prompt_15: Unknown prompt format"
  },
  "Prompt_16": {
    "error": "Failed to process Prompt_16: Unknown prompt format"
  },
  "Prompt_17": {
    "error": "Failed to process Prompt_17: Unknown prompt format"
  },
  "Prompt_18": {
    "error": "Failed to process Prompt_18: Unknown prompt format"
  },
  "Prompt_19": {
    "error": "Failed to process Prompt_19: Unknown prompt format"
  },
  "Prompt_20": {
    "error": "Failed to process Prompt_20: Unknown prompt format"
  },
  "Prompt_21": {
    "error": "Failed to process Prompt_21: Unknown prompt format"
  },
  "Prompt_22": {
    "error": "Failed to process Prompt_22: Unknown prompt format"
  },
  "Prompt_23": {
    "error": "Failed to process Prompt_23: Unknown prompt format"
  },
  "Prompt_24": {
    "error": "Failed to process Prompt_24: Unknown prompt format"
  },
  "Prompt_25": {
    "error": "Failed to process Prompt_25: Unknown prompt format"
  },
  "Prompt_26": {
    "error": "Failed to process Prompt_26: Unknown prompt format"
  },
  "Prompt_27": {
    "error": "Failed to process Prompt_27: Unknown prompt format"
  },
  "Prompt_28": {
    "error": "Failed to process Prompt_28: Unknown prompt format"
  },
  "Prompt_29": {
    "error": "Failed to process Prompt_29: Unknown prompt format"
  },
  "Prompt_30": {
    "error": "Failed to process Prompt_30: Unknown prompt format"
  },
  "Prompt_31": {
    "error": "Failed to process Prompt_31: Unknown prompt format"
  },
  "Prompt_32": {
    "error": "Failed to process Prompt_32: Unknown prompt format"
  },
  "Prompt_33": {
    "error": "Failed to process Prompt_33: Unknown prompt format"
  },
  "Prompt_34": {
    "error": "Failed to process Prompt_34: Unknown prompt format"
  },
  "Prompt_35": {
    "error": "Failed to process Prompt_35: Unknown prompt format"
  },
  "Prompt_36": {
    "error": "Failed to process Prompt_36: Unknown prompt format"
  },
  "Prompt_37": {
    "error": "Failed to process Prompt_37: Unknown prompt format"
  },
  "Prompt_38": {
    "error": "Failed to process Prompt_38: Unknown prompt format"
  },
  "Prompt_39": {
    "error": "Failed to process Prompt_39: Unknown prompt format"
  },
  "Prompt_40": {
    "error": "Failed to process Prompt_40: Unknown prompt format"
  },
  "Prompt_41": {
    "error": "Failed to process Prompt_41: Unknown prompt format"
  },
  "Prompt_42": {
    "error": "Failed to process Prompt_42: Unknown prompt format"
  },
  "Prompt_43": {
    "error": "Failed to process Prompt_43: Unknown prompt format"
  },
  "Prompt_44": {
    "error": "Failed to process Prompt_44: Unknown prompt format"
  },
  "Prompt_45": {
    "error": "Failed to process Prompt_45: Unknown prompt format"
  },
  "Prompt_46": {
    "error": "Failed to process Prompt_46: Unknown prompt format"
  },
  "Prompt_47": {
    "error": "Failed to process Prompt_47: Unknown prompt format"
  },
  "Prompt_48": {
    "error": "Failed to process Prompt_48: Unknown prompt format"
  },
  "Prompt_49": {
    "error": "Failed to process Prompt_49: Unknown prompt format"
  },
  "Prompt_50": {
    "error": "Failed to process Prompt_50: Unknown prompt format"
  }
}